t4racker/__init__.py
t4racker/t4racker.py
t4racker/t4replayer.py
t4racker-0.1.0.dist-info/LICENSE
t4racker-0.1.0.dist-info/METADATA
t4racker-0.1.0.dist-info/WHEEL
t4racker-0.1.0.dist-info/RECORD
